djpay/__init__.py
djpay/api/__init__.py
djpay/api/authorize/__init__.py
djpay/api/authorize/admin.py
djpay/api/authorize/apps.py
djpay/api/authorize/conf.py
djpay/api/authorize/migrations/0001_initial.py
djpay/api/authorize/migrations/0002_alter_paypalinfo_id_alter_paypaltoken_id_and_more.py
djpay/api/authorize/migrations/__init__.py
djpay/api/authorize/models.py
djpay/api/authorize/path.py
djpay/api/authorize/serializers.py
djpay/api/authorize/tests/__init__.py
djpay/api/authorize/tests/apis/__init__.py
djpay/api/authorize/tests/apis/test_authorization_api.py
djpay/api/authorize/tests/apis/test_client.py
djpay/api/authorize/tests/conftest.py
djpay/api/authorize/tests/core/__init__.py
djpay/api/authorize/tests/core/test_custom_conf.py
djpay/api/authorize/tests/factories.py
djpay/api/authorize/tests/models/__init__.py
djpay/api/authorize/tests/models/test_models.py
djpay/api/authorize/tests/models/test_serializers.py
djpay/api/authorize/urls.py
djpay/api/authorize/views.py
djpay/api/subscriptions/__init__.py
djpay/api/subscriptions/apps.py
djpay/api/subscriptions/urls.py
djpay/api/subscriptions/views.py
djpay/utils/__init__.py
djpay/utils/client.py
djpay/utils/helpers.py
djpay/utils/signals.py
dj_py-0.2.2.dist-info/METADATA
dj_py-0.2.2.dist-info/WHEEL
dj_py-0.2.2.dist-info/LICENSE
dj_py-0.2.2.dist-info/RECORD
