Metadata-Version: 2.1
Name: dj-py
Version: 0.2.2
Summary: REST implementation of Django Paypal Authentication System.
Home-page: https://github.com/brahim024/dj-py
License: MIT
Author: Brahim024
Author-email: boughanm6@gmail.com
Maintainer: brahim boughanm
Maintainer-email: boughanm6@gmail.com
Requires-Python: >=3.8,<4.0
Classifier: Development Status :: 5 - Production/Stable
Classifier: Framework :: Django
Classifier: Framework :: Django :: 3.1
Classifier: Framework :: Django :: 3.2
Classifier: Framework :: Django :: 4.0
Classifier: Framework :: Django :: 4.1
Classifier: Framework :: Django :: 4.2
Classifier: Framework :: Django :: 5.0
Classifier: Intended Audience :: Developers
Classifier: License :: OSI Approved :: MIT License
Classifier: Operating System :: OS Independent
Classifier: Programming Language :: Python
Classifier: Programming Language :: Python :: 3
Classifier: Programming Language :: Python :: 3.8
Classifier: Programming Language :: Python :: 3.9
Classifier: Programming Language :: Python :: 3.10
Classifier: Programming Language :: Python :: 3.11
Classifier: Programming Language :: Python :: 3.10
Classifier: Programming Language :: Python :: 3.11
Classifier: Programming Language :: Python :: 3.8
Classifier: Programming Language :: Python :: 3.9
Requires-Dist: django (>=3.0.0)
Requires-Dist: djangorestframework (>=3.9,<4.0)
Requires-Dist: requests (>=2.7,<3.0)
Requires-Dist: webauthn (<1.0)
Project-URL: Repository, https://github.com/brahim024/dj-py
